setup.py
worldpay/__init__.py
worldpay/worldpay.py
worldpay.egg-info/PKG-INFO
worldpay.egg-info/SOURCES.txt
worldpay.egg-info/dependency_links.txt
worldpay.egg-info/not-zip-safe
worldpay.egg-info/top_level.txt