Metadata-Version: 1.0
Name: worldpay
Version: 0.1
Summary: Wrapper for Worldpay Orders API
Home-page: https://github.com/TestingPays
Author: Luke Rickard
Author-email: luke.rickard@thepayment.works
License: MIT
Platform: UNKNOWN
